{
  "project_info": {
    "project_number": "934691089264",
    "project_id": "rytgovendor",
    "storage_bucket": "rytgovendor.firebasestorage.app"
  },
  "client": [
    {
      "client_info": {
        "mobilesdk_app_id": "1:934691089264:android:2c4d14602673beb7d7fdb5",
        "android_client_info": {
          "package_name": "com.rytgovendor"
        }
      },
      "oauth_client": [],
      "api_key": [
        {
          "current_key": "AIzaSyBf5IM0bX4RHAakuHME7HQeu5lLt64zk6s"
        }
      ],
      "services": {
        "appinvite_service": {
          "other_platform_oauth_client": []
        }
      }
    }
  ],
  "configuration_version": "1"
}